{"original_query": "compare math 121 and math 122", "departments": ["MATH"], "course_levels": [[121, 121], [122, 122]], "course_codes": ["MATH 122", "MATH 121"], "terms": [], "constraints": {"max_hours": null, "min_score": null}, "is_followup": true, "referenced_courses": ["MATH 121", "MATH 122"], "preferences": [], "intent": "comparison", "confidence_scores": {"intent": 0.9, "departments": 0.9, "course_levels": 0.4, "course_codes": 0.9, "terms": 0.0, "constraints": 0.0, "preferences": 0.0, "is_followup": 0.7}, "self_reflection": {"missing_information": ["No term/semester specified"], "ambiguities": ["Multiple course levels specified: 121, 122"], "verification_needed": []}, "semantic_aspects": {"difficulty": null, "interest_level": null, "relevance": null, "format": null}, "implicit_preferences": []}